{
  "ids": {
    "ApiConfig": 34
  },
  "models": {
    "ApiConfig": {
      "10": "{\"name\":\"ewrw\",\"public\":true,\"description\":\"Cars public api\",\"entry\":\"/public/cars\",\"methods\":[\"GET\",\"POST\",\"PUT\",\"DELETE\"],\"plugins\":[{\"active\":false,\"settings\":{\"grant\":\"*\"},\"name\":\"authentication\",\"description\":\"Loopback-based authentication middleware\",\"order\":1,\"value\":{\"grant\":\"*\"}},{\"active\":false,\"settings\":{\"etcd_host\":\"env{ETCD_HOST}\",\"etcd_port\":\"4001\",\"mapTo\":\"cars\",\"storage\":\"etcd\"},\"name\":\"discovery\",\"description\":\"Etcd discovery plugin, search service url in the etcd registry by key\",\"order\":2,\"value\":{\"etcd_host\":\"env{ETCD_HOST}\",\"etcd_port\":\"4001\",\"mapTo\":\"cars\",\"storage\":\"etcd\"}},{\"active\":true,\"settings\":{\"target\":\"${target}\",\"withPath\":\"/api/cars\"},\"name\":\"proxy\",\"description\":\"Simple proxying requests\",\"order\":3,\"value\":{\"target\":\"${target}\",\"withPath\":\"/api/cars\"}}],\"config\":{},\"id\":10}",
      "15": "{\"name\":\"Profile api\",\"public\":true,\"description\":\"Profile api\",\"entry\":\"/profiles\",\"methods\":[\"GET\",\"POST\"],\"plugins\":[{\"active\":true,\"settings\":{\"grant\":\"read\"},\"name\":\"authentication\",\"description\":\"Loopback-based authentication middleware\",\"order\":1,\"value\":{\"grant\":\"*\"}},{\"active\":false,\"settings\":{\"etcd_host\":\"env{ETCD_HOST}\",\"etcd_port\":\"4001\",\"mapTo\":\"profile\",\"storage\":\"etcd\"},\"name\":\"discovery\",\"description\":\"Etcd discovery plugin, search service url in the etcd registry by key\",\"order\":2,\"value\":{\"etcd_host\":\"env{ETCD_HOST}\",\"etcd_port\":\"4001\",\"mapTo\":\"profile\",\"storage\":\"etcd\"}},{\"active\":false,\"settings\":{\"target\":\"${target}\",\"withPath\":\"/profiles\"},\"name\":\"proxy\",\"description\":\"Simple proxying requests\",\"order\":3,\"value\":{\"target\":\"${target}\",\"withPath\":\"/profiles\"}}],\"id\":15}",
      "17": "{\"name\":\"tracker\",\"public\":true,\"description\":\"tracker api\",\"entry\":\"/tracker\",\"methods\":[\"GET\",\"POST\"],\"plugins\":[{\"active\":false,\"settings\":{\"grant\":\"*\"},\"name\":\"authentication\",\"description\":\"bla-bla\",\"order\":1,\"value\":{\"grant\":\"*\"}},{\"active\":true,\"settings\":{\"etcd_host\":\"env{ETCD_HOST}\",\"etcd_port\":\"4001\",\"mapTo\":\"tracker\",\"storage\":\"etcd\"},\"name\":\"discovery\",\"description\":\"bla-bla\",\"order\":2,\"value\":{\"etcd_host\":\"env{etcd_host}\",\"etcd_port\":\"4001\",\"mapTo\":\"tracker\",\"storage\":\"etcd\"}},{\"active\":false,\"settings\":{\"target\":\"${target}\",\"withPath\":\"/\"},\"name\":\"proxy\",\"description\":\"proxy\",\"order\":3,\"value\":{\"target\":\"${target}\",\"withPath\":\"/\"}}],\"id\":17}",
      "19": "{\"name\":\"public makers\",\"public\":true,\"entry\":\"/public/makers\",\"methods\":[\"GET\",\"POST\"],\"plugins\":[{\"active\":true,\"settings\":{\"etcd_host\":\"env{ETCD_HOST}\",\"etcd_port\":\"4001\",\"mapTo\":\"cars\",\"storage\":\"etcd\"},\"name\":\"discovery\",\"description\":\"Etcd discovery plugin, search service url in the etcd registry by key\",\"order\":1,\"value\":{\"etcd_host\":\"localhost\",\"etcd_port\":\"4001\",\"mapTo\":\"cars\",\"storage\":\"etcd\"}},{\"active\":false,\"settings\":{\"target\":\"${target}\",\"withPath\":\"/api/makers\"},\"name\":\"proxy\",\"description\":\"Simple proxying requests\",\"order\":2,\"value\":{\"target\":\"${target}\",\"withPath\":\"/api/makers\"}}],\"id\":19}",
      "20": "{\"name\":\"public enginetypes\",\"public\":true,\"entry\":\"/public/enginetypes\",\"methods\":[\"GET\"],\"plugins\":[{\"active\":true,\"settings\":{\"etcd_host\":\"env{ETCD_HOST}\",\"etcd_port\":\"4001\",\"mapTo\":\"cars\",\"storage\":\"etcd\"},\"name\":\"discovery\",\"description\":\"Etcd discovery plugin, search service url in the etcd registry by key\",\"order\":1,\"value\":{\"etcd_host\":\"localhost\",\"etcd_port\":\"4001\",\"mapTo\":\"cars\",\"storage\":\"etcd\"}},{\"active\":false,\"settings\":{\"target\":\"${target}\",\"withPath\":\"/api/enginetypes\"},\"name\":\"proxy\",\"description\":\"Simple proxying requests\",\"order\":2,\"value\":{\"target\":\"${target}\",\"withPath\":\"/api/enginetypes\"}}],\"id\":20}",
      "21": "{\"name\":\"tracker\",\"public\":true,\"entry\":\"/tracks\",\"methods\":[\"GET\"],\"plugins\":[{\"active\":false,\"settings\":{\"etcd_host\":\"env{ETCD_HOST}\",\"etcd_port\":\"4001\",\"mapTo\":\"tracker\",\"storage\":\"etcd\"},\"name\":\"discovery\",\"description\":\"Etcd discovery plugin, search service url in the etcd registry by key\",\"order\":1,\"value\":{\"etcd_host\":\"localhost\",\"etcd_port\":\"4001\",\"mapTo\":\"tracker\",\"storage\":\"etcd\"}},{\"active\":true,\"settings\":{\"target\":\"${target}\",\"withPath\":\"/tracks\"},\"name\":\"proxy\",\"description\":\"Simple proxying requests\",\"order\":2,\"value\":{\"target\":\"${target}\",\"withPath\":\"/\"}}],\"id\":21}",
      "27": "{\"name\":\"/auth\",\"public\":true,\"description\":\"Authentication api\",\"entry\":\"/auth\",\"methods\":[\"POST\"],\"plugins\":[{\"active\":false,\"settings\":{\"grant\":\"*\"},\"name\":\"authentication\",\"description\":\"Loopback-based authentication middleware\",\"order\":1,\"value\":{}},{\"active\":false,\"settings\":{\"etcd_host\":\"env{ETCD_HOST}\",\"etcd_port\":\"4001\",\"mapTo\":\"profile\",\"storage\":\"etcd\"},\"name\":\"discovery\",\"description\":\"Etcd discovery plugin, search service url in the etcd registry by key\",\"order\":2,\"value\":{}},{\"active\":true,\"settings\":{\"target\":\"${target}\",\"withPath\":\"/auth\"},\"name\":\"proxy\",\"description\":\"Simple proxying requests\",\"order\":3,\"value\":{}}],\"id\":27}",
      "28": "{\"name\":\"/users\",\"public\":true,\"description\":\"Users api\",\"entry\":\"/users\",\"methods\":[\"GET\",\"POST\"],\"plugins\":[{\"active\":false,\"settings\":{\"grant\":\"*\"},\"name\":\"authentication\",\"description\":\"Loopback-based authentication middleware\",\"order\":1,\"value\":{}},{\"active\":false,\"settings\":{\"etcd_host\":\"env{ETCD_HOST}\",\"etcd_port\":\"4001\",\"mapTo\":\"profile\",\"storage\":\"etcd\"},\"name\":\"discovery\",\"description\":\"Etcd discovery plugin, search service url in the etcd registry by key\",\"order\":2,\"value\":{}},{\"active\":true,\"settings\":{\"target\":\"${target}\",\"withPath\":\"/users\"},\"name\":\"proxy\",\"description\":\"Simple proxying requests\",\"order\":3,\"value\":{}}],\"id\":28}",
      "29": "{\"name\":\"/image\",\"public\":true,\"description\":\"Image api\",\"entry\":\"/image\",\"methods\":[\"GET\",\"POST\"],\"plugins\":[{\"active\":false,\"settings\":{\"grant\":\"read\"},\"name\":\"authentication\",\"description\":\"Loopback-based authentication middleware\",\"order\":1,\"value\":{\"grant\":\"*\"}},{\"active\":false,\"settings\":{\"etcd_host\":\"env{ETCD_HOST}\",\"etcd_port\":\"4001\",\"mapTo\":\"image\",\"storage\":\"etcd\"},\"name\":\"discovery\",\"description\":\"Etcd discovery plugin, search service url in the etcd registry by key\",\"order\":2,\"value\":{\"etcd_host\":\"env{ETCD_HOST}\",\"etcd_port\":\"4001\",\"mapTo\":\"image\",\"storage\":\"etcd\"}},{\"active\":true,\"settings\":{\"target\":\"${target}\",\"withPath\":\"/api\"},\"name\":\"proxy\",\"description\":\"Simple proxying requests\",\"order\":3,\"value\":{\"target\":\"${target}\",\"withPath\":\"/api\"}}],\"id\":29}",
      "31": "{\"name\":\"/private/cars\",\"public\":true,\"description\":\"private cars api\",\"entry\":\"/private/cars\",\"methods\":[\"GET\",\"POST\",\"PUT\",\"DELETE\"],\"plugins\":[{\"active\":false,\"settings\":{\"grant\":\"read\"},\"name\":\"authentication\",\"description\":\"Loopback-based authentication middleware\",\"order\":1,\"value\":{\"grant\":\"read\"}},{\"active\":false,\"settings\":{\"etcd_host\":\"env{ETCD_HOST}\",\"etcd_port\":\"4001\",\"mapTo\":\"cars\",\"storage\":\"etcd\"},\"name\":\"discovery\",\"description\":\"Etcd discovery plugin, search service url in the etcd registry by key\",\"order\":2,\"value\":{\"etcd_host\":\"env{ETCD_HOST}\",\"etcd_port\":\"4001\",\"mapTo\":\"cars\",\"storage\":\"etcd\"}},{\"active\":true,\"settings\":{\"target\":\"${target}\",\"withPath\":\"/api/cars\"},\"name\":\"proxy\",\"description\":\"Simple proxying requests\",\"order\":3,\"value\":{\"target\":\"${target}\",\"withPath\":\"/api/cars\"}}],\"id\":31}",
      "32": "{\"name\":\"/web\",\"public\":true,\"description\":\"web client api\",\"entry\":\"/\",\"methods\":[\"GET\"],\"plugins\":[{\"active\":false,\"settings\":{\"etcd_host\":\"env{ETCD_HOST}\",\"etcd_port\":\"4001\",\"mapTo\":\"web\",\"storage\":\"etcd\"},\"name\":\"discovery\",\"description\":\"Etcd discovery plugin, search service url in the etcd registry by key\",\"order\":1,\"value\":{}},{\"active\":true,\"settings\":{\"target\":\"${target}\",\"withPath\":\"/\"},\"name\":\"proxy\",\"description\":\"Simple proxying requests\",\"order\":2,\"value\":{}}],\"id\":32}"
    }
  }
}